htctools/__init__.py
htctools/main.py
htctools/modules/Delete_Files_Except_Ordered_Name.py
htctools/modules/Make_POTCAR_And_KPOINTS_GW.py
htctools/modules/Public_Utils.py
htctools/modules/__init__.py
rcs/__init__.py
htctools-0.2.2.dist-info/LICENSE
htctools-0.2.2.dist-info/METADATA
htctools-0.2.2.dist-info/WHEEL
htctools-0.2.2.dist-info/top_level.txt
htctools-0.2.2.dist-info/RECORD
