Metadata-Version: 2.1
Name: htctools
Version: 0.2.2
Summary: A self-use DFT toolbox
Home-page: https://github.com/yourusername/htctools
Author: Tianchang Huang
Author-email: tianchang.huang@monash.edu
License: MIT
Classifier: Programming Language :: Python :: 3
Classifier: License :: OSI Approved :: MIT License
Classifier: Operating System :: OS Independent
Requires-Python: >=3.6
License-File: LICENSE
Requires-Dist: numpy (>=1.19.2)
